README.rst
setup.py
django_attest/__init__.py
django_attest/assertion.py
django_attest/contexts.py
django_attest/environment.py
django_attest/hacks.py
django_attest/reporters.py
django_attest/runner.py
django_attest/signals.py
django_attest/utils.py
django_attest.egg-info/PKG-INFO
django_attest.egg-info/SOURCES.txt
django_attest.egg-info/dependency_links.txt
django_attest.egg-info/entry_points.txt
django_attest.egg-info/requires.txt
django_attest.egg-info/top_level.txt