Metadata-Version: 1.1
Name: django-attest
Version: 0.9.0
Summary: Provides Django specific testing helpers to Attest
Home-page: https://github.com/bradleyayers/django-attest/
Author: Bradley Ayers
Author-email: bradley.ayers@gmail.com
License: Simplified BSD
Platform: UNKNOWN
Classifier: Environment :: Web Environment
Classifier: Framework :: Django
Classifier: Intended Audience :: Developers
Classifier: Operating System :: OS Independent
Classifier: Programming Language :: Python
Classifier: Topic :: Internet :: WWW/HTTP
Classifier: Topic :: Internet :: WWW/HTTP :: Dynamic Content
Classifier: Topic :: Software Development :: Libraries :: Python Modules
